downloader.py
extractor.py
obb_apk_import.py
azlassets/__init__.py
azlassets/classes.py
azlassets/config.py
azlassets/downloader.py
azlassets/imgrecon.py
azlassets/protobuf.py
azlassets/repair.py
azlassets/updater.py
azlassets/versioncontrol.py
azlassets/config/client_config.json
azlassets/config/user_config_template.yml
azlassets/proto/__init__.py
azlassets/proto/p10min_pb_pb2.py
azlassets-3.4.0.dist-info/licenses/LICENSE
azlassets-3.4.0.dist-info/METADATA
azlassets-3.4.0.dist-info/WHEEL
azlassets-3.4.0.dist-info/top_level.txt
azlassets-3.4.0.dist-info/RECORD
