Metadata-Version: 2.4
Name: azlassets
Version: 3.4.0
Summary: Azur Lane asset downloader and extractor
Author: nobbyfix
Project-URL: homepage, https://github.com/nobbyfix/AzurLane-AssetDownloader
Project-URL: repository, https://github.com/nobbyfix/AzurLane-AssetDownloader.git
Project-URL: issues, https://github.com/nobbyfix/AzurLane-AssetDownloader/issues
Project-URL: changelog, https://github.com/nobbyfix/AzurLane-AssetDownloader/blob/master/CHANGELOG.md
Project-URL: download, https://github.com/nobbyfix/AzurLane-AssetDownloader/releases/latest
Keywords: azurlane,azur-lane
Classifier: Development Status :: 5 - Production/Stable
Classifier: Environment :: Console
Classifier: Intended Audience :: Developers
Classifier: Intended Audience :: End Users/Desktop
Classifier: Operating System :: OS Independent
Classifier: Programming Language :: Python
Classifier: Programming Language :: Python :: 3
Classifier: Programming Language :: Python :: 3 :: Only
Classifier: Programming Language :: Python :: 3.11
Classifier: Programming Language :: Python :: 3.12
Classifier: Programming Language :: Python :: 3.13
Classifier: Programming Language :: Python :: 3.14
Classifier: Programming Language :: Python :: 3.15
Classifier: Topic :: Games/Entertainment
Requires-Python: >=3.11
License-File: LICENSE
Requires-Dist: UnityPy>=1.10.18
Requires-Dist: PyYAML
Requires-Dist: Pillow
Requires-Dist: protobuf
Requires-Dist: aiofile
Requires-Dist: aiohttp[speedups]>=3.12
Provides-Extra: dev
Requires-Dist: pre-commit; extra == "dev"
Dynamic: license-file
